{
  "lastDate": "2026-06-15",
  "rows": [
    {
      "tipoTitulo": "Tesouro Selic",
      "dataVencimento": "01/03/2028",
      "dataBase": "15/06/2026",
      "taxaCompra": "0,02",
      "taxaVenda": "0,03",
      "puCompra": 19215.8,
      "puVenda": 19202.19,
      "puBase": 19202.19
    },
    {
      "tipoTitulo": "Tesouro Selic",
      "dataVencimento": "01/03/2029",
      "dataBase": "15/06/2026",
      "taxaCompra": "0,04",
      "taxaVenda": "0,05",
      "puCompra": 19199.58,
      "puVenda": 19184.08,
      "puBase": 19184.08
    },
    {
      "tipoTitulo": "Tesouro Selic",
      "dataVencimento": "01/03/2031",
      "dataBase": "15/06/2026",
      "taxaCompra": "0,07",
      "taxaVenda": "0,08",
      "puCompra": 19155.83,
      "puVenda": 19136.53,
      "puBase": 19136.53
    },
    {
      "tipoTitulo": "Tesouro Selic",
      "dataVencimento": "01/03/2027",
      "dataBase": "15/06/2026",
      "taxaCompra": "0,01",
      "taxaVenda": "0,02",
      "puCompra": 19221.15,
      "puVenda": 19209.46,
      "puBase": 19209.46
    },
    {
      "tipoTitulo": "Tesouro Prefixado",
      "dataVencimento": "01/01/2027",
      "dataBase": "15/06/2026",
      "taxaCompra": "13,98",
      "taxaVenda": "14,10",
      "puCompra": 930.84,
      "puVenda": 929.82,
      "puBase": 929.82
    },
    {
      "tipoTitulo": "Tesouro Prefixado",
      "dataVencimento": "01/01/2029",
      "dataBase": "15/06/2026",
      "taxaCompra": "14,32",
      "taxaVenda": "14,44",
      "puCompra": 712.98,
      "puVenda": 710.71,
      "puBase": 710.71
    },
    {
      "tipoTitulo": "Tesouro Prefixado",
      "dataVencimento": "01/01/2031",
      "dataBase": "15/06/2026",
      "taxaCompra": "14,28",
      "taxaVenda": "14,40",
      "puCompra": 547.28,
      "puVenda": 544.4,
      "puBase": 544.4
    },
    {
      "tipoTitulo": "Tesouro Prefixado",
      "dataVencimento": "01/01/2032",
      "dataBase": "15/06/2026",
      "taxaCompra": "14,31",
      "taxaVenda": "14,43",
      "puCompra": 478.2,
      "puVenda": 475.19,
      "puBase": 475.19
    },
    {
      "tipoTitulo": "Tesouro Prefixado",
      "dataVencimento": "01/01/2028",
      "dataBase": "15/06/2026",
      "taxaCompra": "14,27",
      "taxaVenda": "14,39",
      "puCompra": 813.9,
      "puVenda": 812.15,
      "puBase": 812.15
    },
    {
      "tipoTitulo": "Tesouro IPCA+ com Juros Semestrais",
      "dataVencimento": "15/08/2050",
      "dataBase": "15/06/2026",
      "taxaCompra": "7,26",
      "taxaVenda": "7,38",
      "puCompra": 4184.83,
      "puVenda": 4127.65,
      "puBase": 4127.65
    },
    {
      "tipoTitulo": "Tesouro IPCA+ com Juros Semestrais",
      "dataVencimento": "15/08/2040",
      "dataBase": "15/06/2026",
      "taxaCompra": "7,43",
      "taxaVenda": "7,55",
      "puCompra": 4267.82,
      "puVenda": 4222.52,
      "puBase": 4222.52
    },
    {
      "tipoTitulo": "Tesouro IPCA+ com Juros Semestrais",
      "dataVencimento": "15/08/2030",
      "dataBase": "15/06/2026",
      "taxaCompra": "8,27",
      "taxaVenda": "8,39",
      "puCompra": 4473.64,
      "puVenda": 4453.76,
      "puBase": 4453.76
    },
    {
      "tipoTitulo": "Tesouro IPCA+ com Juros Semestrais",
      "dataVencimento": "15/08/2032",
      "dataBase": "15/06/2026",
      "taxaCompra": "8,07",
      "taxaVenda": "8,19",
      "puCompra": 4378.99,
      "puVenda": 4352.6,
      "puBase": 4352.6
    },
    {
      "tipoTitulo": "Tesouro IPCA+ com Juros Semestrais",
      "dataVencimento": "15/08/2060",
      "dataBase": "15/06/2026",
      "taxaCompra": "7,19",
      "taxaVenda": "7,31",
      "puCompra": 4147.25,
      "puVenda": 4084.57,
      "puBase": 4084.57
    },
    {
      "tipoTitulo": "Tesouro IPCA+ com Juros Semestrais",
      "dataVencimento": "15/05/2035",
      "dataBase": "15/06/2026",
      "taxaCompra": "7,79",
      "taxaVenda": "7,91",
      "puCompra": 4246.84,
      "puVenda": 4212.88,
      "puBase": 4212.88
    },
    {
      "tipoTitulo": "Tesouro IPCA+ com Juros Semestrais",
      "dataVencimento": "15/08/2026",
      "dataBase": "15/06/2026",
      "taxaCompra": "10,94",
      "taxaVenda": "11,06",
      "puCompra": 4784.76,
      "puVenda": 4781.33,
      "puBase": 4781.33
    },
    {
      "tipoTitulo": "Tesouro IPCA+ com Juros Semestrais",
      "dataVencimento": "15/05/2045",
      "dataBase": "15/06/2026",
      "taxaCompra": "7,35",
      "taxaVenda": "7,47",
      "puCompra": 4141.97,
      "puVenda": 4090.11,
      "puBase": 4090.11
    },
    {
      "tipoTitulo": "Tesouro IPCA+ com Juros Semestrais",
      "dataVencimento": "15/05/2055",
      "dataBase": "15/06/2026",
      "taxaCompra": "7,20",
      "taxaVenda": "7,32",
      "puCompra": 4104.53,
      "puVenda": 4044,
      "puBase": 4044
    },
    {
      "tipoTitulo": "Tesouro IPCA+ com Juros Semestrais",
      "dataVencimento": "15/05/2037",
      "dataBase": "15/06/2026",
      "taxaCompra": "7,56",
      "taxaVenda": "7,68",
      "puCompra": 4242.92,
      "puVenda": 4203.96,
      "puBase": 4203.96
    },
    {
      "tipoTitulo": "Tesouro IPCA+",
      "dataVencimento": "15/08/2040",
      "dataBase": "15/06/2026",
      "taxaCompra": "7,25",
      "taxaVenda": "7,37",
      "puCompra": 1764.99,
      "puVenda": 1736.71,
      "puBase": 1736.71
    },
    {
      "tipoTitulo": "Tesouro IPCA+",
      "dataVencimento": "15/08/2026",
      "dataBase": "15/06/2026",
      "taxaCompra": "10,94",
      "taxaVenda": "11,06",
      "puCompra": 4647.37,
      "puVenda": 4644.04,
      "puBase": 4644.04
    },
    {
      "tipoTitulo": "Tesouro IPCA+",
      "dataVencimento": "15/05/2045",
      "dataBase": "15/06/2026",
      "taxaCompra": "7,16",
      "taxaVenda": "7,28",
      "puCompra": 1289.48,
      "puVenda": 1262.14,
      "puBase": 1262.14
    },
    {
      "tipoTitulo": "Tesouro IPCA+",
      "dataVencimento": "15/08/2032",
      "dataBase": "15/06/2026",
      "taxaCompra": "8,04",
      "taxaVenda": "8,16",
      "puCompra": 2944.7,
      "puVenda": 2923.47,
      "puBase": 2923.47
    },
    {
      "tipoTitulo": "Tesouro IPCA+",
      "dataVencimento": "15/05/2029",
      "dataBase": "15/06/2026",
      "taxaCompra": "8,25",
      "taxaVenda": "8,37",
      "puCompra": 3763.76,
      "puVenda": 3750.11,
      "puBase": 3750.11
    },
    {
      "tipoTitulo": "Tesouro IPCA+",
      "dataVencimento": "15/08/2050",
      "dataBase": "15/06/2026",
      "taxaCompra": "7,02",
      "taxaVenda": "7,14",
      "puCompra": 927.54,
      "puVenda": 902.56,
      "puBase": 902.56
    },
    {
      "tipoTitulo": "Tesouro IPCA+",
      "dataVencimento": "15/05/2035",
      "dataBase": "15/06/2026",
      "taxaCompra": "7,70",
      "taxaVenda": "7,82",
      "puCompra": 2453.24,
      "puVenda": 2428.16,
      "puBase": 2428.16
    },
    {
      "tipoTitulo": "Tesouro IGPM+ com Juros Semestrais",
      "dataVencimento": "01/01/2031",
      "dataBase": "15/06/2026",
      "taxaCompra": "8,22",
      "taxaVenda": "8,34",
      "puCompra": 7981.58,
      "puVenda": 7946.82,
      "puBase": 7946.82
    },
    {
      "tipoTitulo": "Tesouro Prefixado com Juros Semestrais",
      "dataVencimento": "01/01/2033",
      "dataBase": "15/06/2026",
      "taxaCompra": "14,34",
      "taxaVenda": "14,46",
      "puCompra": 874.32,
      "puVenda": 869.7,
      "puBase": 869.7
    },
    {
      "tipoTitulo": "Tesouro Prefixado com Juros Semestrais",
      "dataVencimento": "01/01/2027",
      "dataBase": "15/06/2026",
      "taxaCompra": "14,09",
      "taxaVenda": "14,21",
      "puCompra": 1024.29,
      "puVenda": 1023.19,
      "puBase": 1023.19
    },
    {
      "tipoTitulo": "Tesouro Prefixado com Juros Semestrais",
      "dataVencimento": "01/01/2037",
      "dataBase": "15/06/2026",
      "taxaCompra": "14,27",
      "taxaVenda": "14,39",
      "puCompra": 827.32,
      "puVenda": 821.76,
      "puBase": 821.76
    },
    {
      "tipoTitulo": "Tesouro Prefixado com Juros Semestrais",
      "dataVencimento": "01/01/2031",
      "dataBase": "15/06/2026",
      "taxaCompra": "14,35",
      "taxaVenda": "14,47",
      "puCompra": 911.92,
      "puVenda": 908.09,
      "puBase": 908.09
    },
    {
      "tipoTitulo": "Tesouro Prefixado com Juros Semestrais",
      "dataVencimento": "01/01/2035",
      "dataBase": "15/06/2026",
      "taxaCompra": "14,29",
      "taxaVenda": "14,41",
      "puCompra": 848.22,
      "puVenda": 843.04,
      "puBase": 843.04
    },
    {
      "tipoTitulo": "Tesouro Prefixado com Juros Semestrais",
      "dataVencimento": "01/01/2029",
      "dataBase": "15/06/2026",
      "taxaCompra": "14,30",
      "taxaVenda": "14,42",
      "puCompra": 961.39,
      "puVenda": 958.68,
      "puBase": 958.68
    },
    {
      "tipoTitulo": "Tesouro Renda+ Aposentadoria Extra",
      "dataVencimento": "15/12/2059",
      "dataBase": "15/06/2026",
      "taxaCompra": "7,06",
      "taxaVenda": "7,18",
      "puCompra": 1034.05,
      "puVenda": 1009.38,
      "puBase": 1009.38
    },
    {
      "tipoTitulo": "Tesouro Renda+ Aposentadoria Extra",
      "dataVencimento": "15/12/2049",
      "dataBase": "15/06/2026",
      "taxaCompra": "7,41",
      "taxaVenda": "7,53",
      "puCompra": 1963.93,
      "puVenda": 1938.82,
      "puBase": 1938.82
    },
    {
      "tipoTitulo": "Tesouro Renda+ Aposentadoria Extra",
      "dataVencimento": "15/12/2069",
      "dataBase": "15/06/2026",
      "taxaCompra": "6,93",
      "taxaVenda": "7,05",
      "puCompra": 545.22,
      "puVenda": 526.29,
      "puBase": 526.29
    },
    {
      "tipoTitulo": "Tesouro Renda+ Aposentadoria Extra",
      "dataVencimento": "15/12/2064",
      "dataBase": "15/06/2026",
      "taxaCompra": "6,99",
      "taxaVenda": "7,11",
      "puCompra": 749.56,
      "puVenda": 727.59,
      "puBase": 727.59
    },
    {
      "tipoTitulo": "Tesouro Renda+ Aposentadoria Extra",
      "dataVencimento": "15/12/2054",
      "dataBase": "15/06/2026",
      "taxaCompra": "7,19",
      "taxaVenda": "7,31",
      "puCompra": 1423.15,
      "puVenda": 1397.04,
      "puBase": 1397.04
    },
    {
      "tipoTitulo": "Tesouro Renda+ Aposentadoria Extra",
      "dataVencimento": "15/12/2074",
      "dataBase": "15/06/2026",
      "taxaCompra": "6,91",
      "taxaVenda": "7,03",
      "puCompra": 393.45,
      "puVenda": 377.66,
      "puBase": 377.66
    },
    {
      "tipoTitulo": "Tesouro Renda+ Aposentadoria Extra",
      "dataVencimento": "15/12/2084",
      "dataBase": "15/06/2026",
      "taxaCompra": "6,91",
      "taxaVenda": "7,03",
      "puCompra": 202.5,
      "puVenda": 192.22,
      "puBase": 192.22
    },
    {
      "tipoTitulo": "Tesouro Renda+ Aposentadoria Extra",
      "dataVencimento": "15/12/2079",
      "dataBase": "15/06/2026",
      "taxaCompra": "6,91",
      "taxaVenda": "7,03",
      "puCompra": 282.25,
      "puVenda": 269.42,
      "puBase": 269.42
    },
    {
      "tipoTitulo": "Tesouro Educa+",
      "dataVencimento": "15/12/2046",
      "dataBase": "15/06/2026",
      "taxaCompra": "7,17",
      "taxaVenda": "7,29",
      "puCompra": 1373.24,
      "puVenda": 1345.64,
      "puBase": 1345.64
    },
    {
      "tipoTitulo": "Tesouro Educa+",
      "dataVencimento": "15/12/2044",
      "dataBase": "15/06/2026",
      "taxaCompra": "7,22",
      "taxaVenda": "7,34",
      "puCompra": 1564.3,
      "puVenda": 1536.28,
      "puBase": 1536.28
    },
    {
      "tipoTitulo": "Tesouro Educa+",
      "dataVencimento": "15/12/2041",
      "dataBase": "15/06/2026",
      "taxaCompra": "7,31",
      "taxaVenda": "7,43",
      "puCompra": 1905.83,
      "puVenda": 1877.97,
      "puBase": 1877.97
    },
    {
      "tipoTitulo": "Tesouro Educa+",
      "dataVencimento": "15/12/2039",
      "dataBase": "15/06/2026",
      "taxaCompra": "7,45",
      "taxaVenda": "7,57",
      "puCompra": 2162.39,
      "puVenda": 2135.56,
      "puBase": 2135.56
    },
    {
      "tipoTitulo": "Tesouro Educa+",
      "dataVencimento": "15/12/2048",
      "dataBase": "15/06/2026",
      "taxaCompra": "7,13",
      "taxaVenda": "7,25",
      "puCompra": 1205.81,
      "puVenda": 1178.94,
      "puBase": 1178.94
    },
    {
      "tipoTitulo": "Tesouro Educa+",
      "dataVencimento": "15/12/2043",
      "dataBase": "15/06/2026",
      "taxaCompra": "7,24",
      "taxaVenda": "7,36",
      "puCompra": 1672.08,
      "puVenda": 1643.96,
      "puBase": 1643.96
    },
    {
      "tipoTitulo": "Tesouro Educa+",
      "dataVencimento": "15/12/2038",
      "dataBase": "15/06/2026",
      "taxaCompra": "7,54",
      "taxaVenda": "7,66",
      "puCompra": 2303.06,
      "puVenda": 2277.02,
      "puBase": 2277.02
    },
    {
      "tipoTitulo": "Tesouro Educa+",
      "dataVencimento": "15/12/2045",
      "dataBase": "15/06/2026",
      "taxaCompra": "7,20",
      "taxaVenda": "7,32",
      "puCompra": 1464.12,
      "puVenda": 1436.29,
      "puBase": 1436.29
    },
    {
      "tipoTitulo": "Tesouro Educa+",
      "dataVencimento": "15/12/2033",
      "dataBase": "15/06/2026",
      "taxaCompra": "8,10",
      "taxaVenda": "8,22",
      "puCompra": 3223.53,
      "puVenda": 3204.87,
      "puBase": 3204.87
    },
    {
      "tipoTitulo": "Tesouro Educa+",
      "dataVencimento": "15/12/2030",
      "dataBase": "15/06/2026",
      "taxaCompra": "8,30",
      "taxaVenda": "8,42",
      "puCompra": 3570.73,
      "puVenda": 3560.72,
      "puBase": 3560.72
    },
    {
      "tipoTitulo": "Tesouro Educa+",
      "dataVencimento": "15/12/2036",
      "dataBase": "15/06/2026",
      "taxaCompra": "7,78",
      "taxaVenda": "7,90",
      "puCompra": 2614.47,
      "puVenda": 2590.67,
      "puBase": 2590.67
    },
    {
      "tipoTitulo": "Tesouro Educa+",
      "dataVencimento": "15/12/2037",
      "dataBase": "15/06/2026",
      "taxaCompra": "7,66",
      "taxaVenda": "7,78",
      "puCompra": 2450.88,
      "puVenda": 2425.87,
      "puBase": 2425.87
    },
    {
      "tipoTitulo": "Tesouro Educa+",
      "dataVencimento": "15/12/2035",
      "dataBase": "15/06/2026",
      "taxaCompra": "7,90",
      "taxaVenda": "8,02",
      "puCompra": 2795.4,
      "puVenda": 2773.05,
      "puBase": 2773.05
    },
    {
      "tipoTitulo": "Tesouro Educa+",
      "dataVencimento": "15/12/2031",
      "dataBase": "15/06/2026",
      "taxaCompra": "8,24",
      "taxaVenda": "8,36",
      "puCompra": 3749.51,
      "puVenda": 3736.05,
      "puBase": 3736.05
    },
    {
      "tipoTitulo": "Tesouro Educa+",
      "dataVencimento": "15/12/2042",
      "dataBase": "15/06/2026",
      "taxaCompra": "7,27",
      "taxaVenda": "7,39",
      "puCompra": 1785.78,
      "puVenda": 1757.71,
      "puBase": 1757.71
    },
    {
      "tipoTitulo": "Tesouro Educa+",
      "dataVencimento": "15/12/2032",
      "dataBase": "15/06/2026",
      "taxaCompra": "8,18",
      "taxaVenda": "8,30",
      "puCompra": 3473.07,
      "puVenda": 3456.78,
      "puBase": 3456.78
    },
    {
      "tipoTitulo": "Tesouro Educa+",
      "dataVencimento": "15/12/2047",
      "dataBase": "15/06/2026",
      "taxaCompra": "7,15",
      "taxaVenda": "7,27",
      "puCompra": 1286.56,
      "puVenda": 1259.3,
      "puBase": 1259.3
    },
    {
      "tipoTitulo": "Tesouro Educa+",
      "dataVencimento": "15/12/2034",
      "dataBase": "15/06/2026",
      "taxaCompra": "8,01",
      "taxaVenda": "8,13",
      "puCompra": 2997.37,
      "puVenda": 2976.72,
      "puBase": 2976.72
    },
    {
      "tipoTitulo": "Tesouro Educa+",
      "dataVencimento": "15/12/2040",
      "dataBase": "15/06/2026",
      "taxaCompra": "7,37",
      "taxaVenda": "7,49",
      "puCompra": 2031.01,
      "puVenda": 2003.57,
      "puBase": 2003.57
    }
  ],
  "updatedAt": "2026-06-16T23:06:38.030Z"
}